{"city": {"city": "Биробиджан", "slug": "russia/birobidzhan"}, "count": 5, "hotels": [{"ota_hotel_id": "hotel_vostok", "master_id": "hotel_vostok", "latitude": 48.788425, "longitude": 132.93477, "rating": 8.3, "price": 6800}, {"ota_hotel_id": "bira_mini", "master_id": "bira_mini", "latitude": 48.790165, "longitude": 132.93463, "rating": 8.1, "price": 10000}, {"ota_hotel_id": "barbaris", "master_id": "barbaris", "latitude": 48.80559, "longitude": 132.89592, "rating": 7.9, "price": 4357}, {"ota_hotel_id": "bira", "master_id": "bira", "latitude": 48.78446, "longitude": 132.937, "rating": 8.3, "price": 11953}, {"ota_hotel_id": "smart_hotel_kdo_birobidzhan_hotel", "master_id": "smart_hotel_kdo_birobidzhan_hotel", "latitude": 48.79291, "longitude": 132.93454, "rating": 0, "price": 2495}], "url": "https://ostrovok.ru/hotel/russia/birobidzhan/?guests=1&map=true&distance=999&type_group=apart_hotel.hotel.hostel&dates=08.09.2023-12.09.2023", "full_hotels_list": true}